nvm_run/__init__.py
nvm_run/main.py
nvm_run-1.0.1.dist-info/METADATA
nvm_run-1.0.1.dist-info/WHEEL
nvm_run-1.0.1.dist-info/entry_points.txt
nvm_run-1.0.1.dist-info/top_level.txt
nvm_run-1.0.1.dist-info/RECORD
