Metadata-Version: 2.4
Name: nvm-run
Version: 1.0.1
Summary: Just run a particular version of node using nvm
Author-email: "@readwithai" <talwrii@gmail.com>
License: MIT
Requires-Python: >=3.7
